vesselapi/__init__.py
vesselapi/accounts.py
vesselapi/attendees.py
vesselapi/calls.py
vesselapi/connections.py
vesselapi/contacts.py
vesselapi/deals.py
vesselapi/emails.py
vesselapi/events.py
vesselapi/integrations.py
vesselapi/leads.py
vesselapi/links.py
vesselapi/notes.py
vesselapi/passthrough.py
vesselapi/sdk.py
vesselapi/sdkconfiguration.py
vesselapi/tasks.py
vesselapi/tokens.py
vesselapi/users.py
vesselapi/webhooks.py
vesselapi/models/__init__.py
vesselapi/models/errors/__init__.py
vesselapi/models/errors/sdkerror.py
vesselapi/models/operations/__init__.py
vesselapi/models/operations/delete_connection.py
vesselapi/models/operations/delete_webhook.py
vesselapi/models/operations/get_all_crm_accounts.py
vesselapi/models/operations/get_all_crm_calls.py
vesselapi/models/operations/get_all_crm_connections.py
vesselapi/models/operations/get_all_crm_contacts.py
vesselapi/models/operations/get_all_crm_deals.py
vesselapi/models/operations/get_all_crm_emails.py
vesselapi/models/operations/get_all_crm_event_attendees.py
vesselapi/models/operations/get_all_crm_events.py
vesselapi/models/operations/get_all_crm_integrations.py
vesselapi/models/operations/get_all_crm_leads.py
vesselapi/models/operations/get_all_crm_notes.py
vesselapi/models/operations/get_all_crm_tasks.py
vesselapi/models/operations/get_all_crm_users.py
vesselapi/models/operations/get_batch_crm_account.py
vesselapi/models/operations/get_batch_crm_call.py
vesselapi/models/operations/get_batch_crm_contact.py
vesselapi/models/operations/get_batch_crm_deal.py
vesselapi/models/operations/get_batch_crm_email.py
vesselapi/models/operations/get_batch_crm_event.py
vesselapi/models/operations/get_batch_crm_event_attendee.py
vesselapi/models/operations/get_batch_crm_lead.py
vesselapi/models/operations/get_batch_crm_note.py
vesselapi/models/operations/get_batch_crm_task.py
vesselapi/models/operations/get_batch_crm_user.py
vesselapi/models/operations/get_details_crm_account.py
vesselapi-5.2.1.dist-info/METADATA
vesselapi-5.2.1.dist-info/WHEEL
vesselapi-5.2.1.dist-info/top_level.txt
vesselapi-5.2.1.dist-info/RECORD
